{
  "SimulationTime": "11.19055221s",
  "SimulationTimeInSeconds": 11.19055221,
  "TotalCycles": 100000,
  "CyclesPerSecond": 8936.109507682642,
  "PacketsPerSecond": 2369.76688034236,
  "NumPacketsReceived": 26538,
  "NumPacketsTransmitted": 26519,
  "Throughput": 0.00414359375,
  "AveragePacketDelay": 87.5278479580678,
  "AveragePacketHops": 8.081073946981409,
  "MaxPacketDelay": 379,
  "MaxPacketHops": 14,
  "NumPayloadPacketsReceived": 24056,
  "NumPayloadPacketsTransmitted": 24038,
  "PayloadThroughput": 0.0037559375,
  "AveragePayloadPacketDelay": 93.06731009235378,
  "AveragePayloadPacketHops": 8.249313586820866,
  "MaxPayloadPacketDelay": 379,
  "MaxPayloadPacketHops": 14,
  "AverageFlitPerStateDelay[INPUT_BUFFER]": 3.8993762901307085,
  "AverageFlitPerStateDelay[ROUTE_COMPUTATION]": 1.298195370184661,
  "AverageFlitPerStateDelay[VIRTUAL_CHANNEL_ALLOCATION]": 1.095894883647168,
  "AverageFlitPerStateDelay[SWITCH_ALLOCATION]": 1,
  "AverageFlitPerStateDelay[SWITCH_TRAVERSAL]": 1.1540129267533392,
  "AverageFlitPerStateDelay[LINK_TRAVERSAL]": 4.21831538727748,
  "AverageFlitPerStateDelay[DESTINATION_ARRIVED]": 0,
  "MaxFlitPerStateDelay[INPUT_BUFFER]": 59,
  "MaxFlitPerStateDelay[ROUTE_COMPUTATION]": 39,
  "MaxFlitPerStateDelay[VIRTUAL_CHANNEL_ALLOCATION]": 5,
  "MaxFlitPerStateDelay[SWITCH_ALLOCATION]": 1,
  "MaxFlitPerStateDelay[SWITCH_TRAVERSAL]": 40,
  "MaxFlitPerStateDelay[LINK_TRAVERSAL]": 90,
  "MaxFlitPerStateDelay[DESTINATION_ARRIVED]": 0
}