{
  "SimulationTime": "25m37.778586584s",
  "SimulationTimeInSeconds": 1537.778586584,
  "TotalCycles": 10000000,
  "CyclesPerSecond": 6502.886753166371,
  "PacketsPerSecond": 1725.74323973072,
  "NumPacketsReceived": 2653854,
  "NumPacketsTransmitted": 2653811,
  "Throughput": 0.0041465796875,
  "AveragePacketDelay": 89.81691009646127,
  "AveragePacketHops": 8.28792592991739,
  "MaxPacketDelay": 1350,
  "MaxPacketHops": 15,
  "NumPayloadPacketsReceived": 2397199,
  "NumPayloadPacketsTransmitted": 2397158,
  "PayloadThroughput": 0.003745559375,
  "AveragePayloadPacketDelay": 95.88772538147256,
  "AveragePayloadPacketHops": 8.497325165883934,
  "MaxPayloadPacketDelay": 1350,
  "MaxPayloadPacketHops": 14,
  "AverageFlitPerStateDelay[INPUT_BUFFER]": 3.871566427664139,
  "AverageFlitPerStateDelay[ROUTE_COMPUTATION]": 1.2822362111560135,
  "AverageFlitPerStateDelay[VIRTUAL_CHANNEL_ALLOCATION]": 1.0882590978257949,
  "AverageFlitPerStateDelay[SWITCH_ALLOCATION]": 1,
  "AverageFlitPerStateDelay[SWITCH_TRAVERSAL]": 1.1627806004714536,
  "AverageFlitPerStateDelay[LINK_TRAVERSAL]": 4.26714534169223,
  "AverageFlitPerStateDelay[DESTINATION_ARRIVED]": 0,
  "MaxFlitPerStateDelay[INPUT_BUFFER]": 193,
  "MaxFlitPerStateDelay[ROUTE_COMPUTATION]": 116,
  "MaxFlitPerStateDelay[VIRTUAL_CHANNEL_ALLOCATION]": 5,
  "MaxFlitPerStateDelay[SWITCH_ALLOCATION]": 1,
  "MaxFlitPerStateDelay[SWITCH_TRAVERSAL]": 135,
  "MaxFlitPerStateDelay[LINK_TRAVERSAL]": 272,
  "MaxFlitPerStateDelay[DESTINATION_ARRIVED]": 0
}