{
  "SimulationTime": "10m20.522213946s",
  "SimulationTimeInSeconds": 620.522213946,
  "TotalCycles": 10000000,
  "CyclesPerSecond": 16115.458520668262,
  "PacketsPerSecond": 2419.964936389333,
  "NumPacketsReceived": 1501649,
  "NumPacketsTransmitted": 1501642,
  "Throughput": 0.002346315625,
  "AveragePacketDelay": 53.93447173161113,
  "AveragePacketHops": 8.9231807581301,
  "MaxPacketDelay": 132,
  "MaxPacketHops": 15,
  "NumPayloadPacketsReceived": 1501649,
  "NumPayloadPacketsTransmitted": 1501642,
  "PayloadThroughput": 0.002346315625,
  "AveragePayloadPacketDelay": 53.93447173161113,
  "AveragePayloadPacketHops": 8.9231807581301,
  "MaxPayloadPacketDelay": 132,
  "MaxPayloadPacketHops": 15,
  "AverageFlitPerStateDelay[INPUT_BUFFER]": 2.1122301020032634,
  "AverageFlitPerStateDelay[ROUTE_COMPUTATION]": 1.0086096804555889,
  "AverageFlitPerStateDelay[VIRTUAL_CHANNEL_ALLOCATION]": 1.0330156039217127,
  "AverageFlitPerStateDelay[SWITCH_ALLOCATION]": 1,
  "AverageFlitPerStateDelay[SWITCH_TRAVERSAL]": 1.0000229113949934,
  "AverageFlitPerStateDelay[LINK_TRAVERSAL]": 1.0095925697203327,
  "AverageFlitPerStateDelay[DESTINATION_ARRIVED]": 0,
  "MaxFlitPerStateDelay[INPUT_BUFFER]": 33,
  "MaxFlitPerStateDelay[ROUTE_COMPUTATION]": 23,
  "MaxFlitPerStateDelay[VIRTUAL_CHANNEL_ALLOCATION]": 5,
  "MaxFlitPerStateDelay[SWITCH_ALLOCATION]": 1,
  "MaxFlitPerStateDelay[SWITCH_TRAVERSAL]": 11,
  "MaxFlitPerStateDelay[LINK_TRAVERSAL]": 38,
  "MaxFlitPerStateDelay[DESTINATION_ARRIVED]": 0
}