{
  "SimulationTime": "9.763770617s",
  "SimulationTimeInSeconds": 9.763770617,
  "TotalCycles": 100000,
  "CyclesPerSecond": 10241.944830810233,
  "PacketsPerSecond": 2304.4375869323026,
  "NumPacketsReceived": 22516,
  "NumPacketsTransmitted": 22500,
  "Throughput": 0.003515625,
  "AveragePacketDelay": 54.92715555555556,
  "AveragePacketHops": 8.492222222222223,
  "MaxPacketDelay": 171,
  "MaxPacketHops": 14,
  "NumPayloadPacketsReceived": 20034,
  "NumPayloadPacketsTransmitted": 20019,
  "PayloadThroughput": 0.00312796875,
  "AveragePayloadPacketDelay": 57.656726110195315,
  "AveragePayloadPacketHops": 8.745192067535841,
  "MaxPayloadPacketDelay": 171,
  "MaxPayloadPacketHops": 14,
  "AverageFlitPerStateDelay[INPUT_BUFFER]": 2.366036661446863,
  "AverageFlitPerStateDelay[ROUTE_COMPUTATION]": 1.0337239719577274,
  "AverageFlitPerStateDelay[VIRTUAL_CHANNEL_ALLOCATION]": 1.0631539845973548,
  "AverageFlitPerStateDelay[SWITCH_ALLOCATION]": 1,
  "AverageFlitPerStateDelay[SWITCH_TRAVERSAL]": 1.0022247810460938,
  "AverageFlitPerStateDelay[LINK_TRAVERSAL]": 1.177556013737031,
  "AverageFlitPerStateDelay[DESTINATION_ARRIVED]": 0,
  "MaxFlitPerStateDelay[INPUT_BUFFER]": 34,
  "MaxFlitPerStateDelay[ROUTE_COMPUTATION]": 23,
  "MaxFlitPerStateDelay[VIRTUAL_CHANNEL_ALLOCATION]": 4,
  "MaxFlitPerStateDelay[SWITCH_ALLOCATION]": 1,
  "MaxFlitPerStateDelay[SWITCH_TRAVERSAL]": 17,
  "MaxFlitPerStateDelay[LINK_TRAVERSAL]": 44,
  "MaxFlitPerStateDelay[DESTINATION_ARRIVED]": 0
}