{
  "SimulationTime": "14m10.440704096s",
  "SimulationTimeInSeconds": 850.440704096,
  "TotalCycles": 10000000,
  "CyclesPerSecond": 11758.60933259278,
  "PacketsPerSecond": 2649.8190751528487,
  "NumPacketsReceived": 2253529,
  "NumPacketsTransmitted": 2253514,
  "Throughput": 0.003521115625,
  "AveragePacketDelay": 53.3064618191855,
  "AveragePacketHops": 8.253126450512399,
  "MaxPacketDelay": 228,
  "MaxPacketHops": 15,
  "NumPayloadPacketsReceived": 1996874,
  "NumPayloadPacketsTransmitted": 1996861,
  "PayloadThroughput": 0.0031200953125,
  "AveragePayloadPacketDelay": 56.00505894000634,
  "AveragePayloadPacketHops": 8.500029796766023,
  "MaxPayloadPacketDelay": 228,
  "MaxPayloadPacketHops": 14,
  "AverageFlitPerStateDelay[INPUT_BUFFER]": 2.350129602868192,
  "AverageFlitPerStateDelay[ROUTE_COMPUTATION]": 1.0394419366398717,
  "AverageFlitPerStateDelay[VIRTUAL_CHANNEL_ALLOCATION]": 1.0500401051648935,
  "AverageFlitPerStateDelay[SWITCH_ALLOCATION]": 1,
  "AverageFlitPerStateDelay[SWITCH_TRAVERSAL]": 1.0026390957611275,
  "AverageFlitPerStateDelay[LINK_TRAVERSAL]": 1.1674338665086637,
  "AverageFlitPerStateDelay[DESTINATION_ARRIVED]": 0,
  "MaxFlitPerStateDelay[INPUT_BUFFER]": 43,
  "MaxFlitPerStateDelay[ROUTE_COMPUTATION]": 31,
  "MaxFlitPerStateDelay[VIRTUAL_CHANNEL_ALLOCATION]": 5,
  "MaxFlitPerStateDelay[SWITCH_ALLOCATION]": 1,
  "MaxFlitPerStateDelay[SWITCH_TRAVERSAL]": 29,
  "MaxFlitPerStateDelay[LINK_TRAVERSAL]": 63,
  "MaxFlitPerStateDelay[DESTINATION_ARRIVED]": 0
}