{
  "SimulationTime": "1.356723472s",
  "SimulationTimeInSeconds": 1.356723472,
  "TotalCycles": 1000,
  "CyclesPerSecond": 737.0698750614672,
  "PacketsPerSecond": 3955.1169495798326,
  "NumPacketsReceived": 5698,
  "NumPacketsTransmitted": 5366,
  "Throughput": 0.08384375,
  "AveragePacketDelay": 55.43663809168841,
  "AveragePacketHops": 6.295378307864331,
  "MaxPacketDelay": 221,
  "MaxPacketHops": 15,
  "NumPayloadPacketsReceived": 5678,
  "NumPayloadPacketsTransmitted": 5346,
  "PayloadThroughput": 0.08353125,
  "AveragePayloadPacketDelay": 55.47362514029181,
  "AveragePayloadPacketHops": 6.300224466891134,
  "MaxPayloadPacketDelay": 221,
  "MaxPayloadPacketHops": 15,
  "AverageFlitPerStateDelay[INPUT_BUFFER]": 3.885214077464738,
  "AverageFlitPerStateDelay[ROUTE_COMPUTATION]": 1.58140527618885,
  "AverageFlitPerStateDelay[VIRTUAL_CHANNEL_ALLOCATION]": 1.2984270815524022,
  "AverageFlitPerStateDelay[SWITCH_ALLOCATION]": 1,
  "AverageFlitPerStateDelay[SWITCH_TRAVERSAL]": 1.0150792396442478,
  "AverageFlitPerStateDelay[LINK_TRAVERSAL]": 1.9101507280933323,
  "AverageFlitPerStateDelay[DESTINATION_ARRIVED]": 0,
  "MaxFlitPerStateDelay[INPUT_BUFFER]": 54,
  "MaxFlitPerStateDelay[ROUTE_COMPUTATION]": 37,
  "MaxFlitPerStateDelay[VIRTUAL_CHANNEL_ALLOCATION]": 5,
  "MaxFlitPerStateDelay[SWITCH_ALLOCATION]": 1,
  "MaxFlitPerStateDelay[SWITCH_TRAVERSAL]": 32,
  "MaxFlitPerStateDelay[LINK_TRAVERSAL]": 68,
  "MaxFlitPerStateDelay[DESTINATION_ARRIVED]": 0
}