{
  "SimulationTime": "27.02047659s",
  "SimulationTimeInSeconds": 27.02047659,
  "TotalCycles": 100000,
  "CyclesPerSecond": 3700.8969722247225,
  "PacketsPerSecond": 1015.8222009362419,
  "NumPacketsReceived": 27545,
  "NumPacketsTransmitted": 27448,
  "Throughput": 0.00428875,
  "AveragePacketDelay": 330.52404546779366,
  "AveragePacketHops": 8.367968522296707,
  "MaxPacketDelay": 2309,
  "MaxPacketHops": 14,
  "NumPayloadPacketsReceived": 25064,
  "NumPayloadPacketsTransmitted": 24969,
  "PayloadThroughput": 0.00390140625,
  "AveragePayloadPacketDelay": 357.83867996315433,
  "AveragePayloadPacketHops": 8.558332332091794,
  "MaxPayloadPacketDelay": 2309,
  "MaxPayloadPacketHops": 13,
  "AverageFlitPerStateDelay[INPUT_BUFFER]": 12.929393558260424,
  "AverageFlitPerStateDelay[ROUTE_COMPUTATION]": 3.982441892783935,
  "AverageFlitPerStateDelay[VIRTUAL_CHANNEL_ALLOCATION]": 1.1363583064435576,
  "AverageFlitPerStateDelay[SWITCH_ALLOCATION]": 1,
  "AverageFlitPerStateDelay[SWITCH_TRAVERSAL]": 3.1656001557953584,
  "AverageFlitPerStateDelay[LINK_TRAVERSAL]": 24.880937607900456,
  "AverageFlitPerStateDelay[DESTINATION_ARRIVED]": 0,
  "MaxFlitPerStateDelay[INPUT_BUFFER]": 321,
  "MaxFlitPerStateDelay[ROUTE_COMPUTATION]": 176,
  "MaxFlitPerStateDelay[VIRTUAL_CHANNEL_ALLOCATION]": 5,
  "MaxFlitPerStateDelay[SWITCH_ALLOCATION]": 1,
  "MaxFlitPerStateDelay[SWITCH_TRAVERSAL]": 180,
  "MaxFlitPerStateDelay[LINK_TRAVERSAL]": 485,
  "MaxFlitPerStateDelay[DESTINATION_ARRIVED]": 0
}