{
  "SimulationTime": "13m50.775567536s",
  "SimulationTimeInSeconds": 830.775567536,
  "TotalCycles": 1000000,
  "CyclesPerSecond": 1203.6945224158471,
  "PacketsPerSecond": 4653.403579821186,
  "NumPacketsReceived": 3866113,
  "NumPacketsTransmitted": 3865934,
  "Throughput": 0.06040521875,
  "AveragePacketDelay": 41.517621873523964,
  "AveragePacketHops": 6.333262544057917,
  "MaxPacketDelay": 199,
  "MaxPacketHops": 15,
  "NumPayloadPacketsReceived": 3840166,
  "NumPayloadPacketsTransmitted": 3839990,
  "PayloadThroughput": 0.05999984375,
  "AveragePayloadPacketDelay": 41.5541118596663,
  "AveragePayloadPacketHops": 6.333363628551116,
  "MaxPayloadPacketDelay": 199,
  "MaxPayloadPacketHops": 15,
  "AverageFlitPerStateDelay[INPUT_BUFFER]": 2.569986149635229,
  "AverageFlitPerStateDelay[ROUTE_COMPUTATION]": 1.1207782347934687,
  "AverageFlitPerStateDelay[VIRTUAL_CHANNEL_ALLOCATION]": 1.1484897996358128,
  "AverageFlitPerStateDelay[SWITCH_ALLOCATION]": 1,
  "AverageFlitPerStateDelay[SWITCH_TRAVERSAL]": 1.000156024484638,
  "AverageFlitPerStateDelay[LINK_TRAVERSAL]": 1.0384694261975096,
  "AverageFlitPerStateDelay[DESTINATION_ARRIVED]": 0,
  "MaxFlitPerStateDelay[INPUT_BUFFER]": 59,
  "MaxFlitPerStateDelay[ROUTE_COMPUTATION]": 48,
  "MaxFlitPerStateDelay[VIRTUAL_CHANNEL_ALLOCATION]": 5,
  "MaxFlitPerStateDelay[SWITCH_ALLOCATION]": 1,
  "MaxFlitPerStateDelay[SWITCH_TRAVERSAL]": 39,
  "MaxFlitPerStateDelay[LINK_TRAVERSAL]": 85,
  "MaxFlitPerStateDelay[DESTINATION_ARRIVED]": 0
}