{
  "SimulationTime": "13m54.768909682s",
  "SimulationTimeInSeconds": 834.768909682,
  "TotalCycles": 10000000,
  "CyclesPerSecond": 11979.36325133316,
  "PacketsPerSecond": 2397.6012723837994,
  "NumPacketsReceived": 2001451,
  "NumPacketsTransmitted": 2001443,
  "Throughput": 0.0031272546875,
  "AveragePacketDelay": 59.20831270238523,
  "AveragePacketHops": 8.921076443346125,
  "MaxPacketDelay": 259,
  "MaxPacketHops": 15,
  "NumPayloadPacketsReceived": 2001451,
  "NumPayloadPacketsTransmitted": 2001443,
  "PayloadThroughput": 0.0031272546875,
  "AveragePayloadPacketDelay": 59.20831270238523,
  "AveragePayloadPacketHops": 8.921076443346125,
  "MaxPayloadPacketDelay": 259,
  "MaxPayloadPacketHops": 15,
  "AverageFlitPerStateDelay[INPUT_BUFFER]": 2.422006577236775,
  "AverageFlitPerStateDelay[ROUTE_COMPUTATION]": 1.0484101100236392,
  "AverageFlitPerStateDelay[VIRTUAL_CHANNEL_ALLOCATION]": 1.0592495543702962,
  "AverageFlitPerStateDelay[SWITCH_ALLOCATION]": 1,
  "AverageFlitPerStateDelay[SWITCH_TRAVERSAL]": 1.0033566249058232,
  "AverageFlitPerStateDelay[LINK_TRAVERSAL]": 1.2218941653305495,
  "AverageFlitPerStateDelay[DESTINATION_ARRIVED]": 0,
  "MaxFlitPerStateDelay[INPUT_BUFFER]": 39,
  "MaxFlitPerStateDelay[ROUTE_COMPUTATION]": 29,
  "MaxFlitPerStateDelay[VIRTUAL_CHANNEL_ALLOCATION]": 5,
  "MaxFlitPerStateDelay[SWITCH_ALLOCATION]": 1,
  "MaxFlitPerStateDelay[SWITCH_TRAVERSAL]": 26,
  "MaxFlitPerStateDelay[LINK_TRAVERSAL]": 66,
  "MaxFlitPerStateDelay[DESTINATION_ARRIVED]": 0
}