{
  "SimulationTime": "8.883303093s",
  "SimulationTimeInSeconds": 8.883303093,
  "TotalCycles": 100000,
  "CyclesPerSecond": 11257.073968217916,
  "PacketsPerSecond": 2360.9461233543434,
  "NumPacketsReceived": 20984,
  "NumPacketsTransmitted": 20973,
  "Throughput": 0.00327703125,
  "AveragePacketDelay": 59.09784008010299,
  "AveragePacketHops": 8.617174462404043,
  "MaxPacketDelay": 165,
  "MaxPacketHops": 13,
  "NumPayloadPacketsReceived": 20984,
  "NumPayloadPacketsTransmitted": 20973,
  "PayloadThroughput": 0.00327703125,
  "AveragePayloadPacketDelay": 59.09784008010299,
  "AveragePayloadPacketHops": 8.617174462404043,
  "MaxPayloadPacketDelay": 165,
  "MaxPayloadPacketHops": 13,
  "AverageFlitPerStateDelay[INPUT_BUFFER]": 2.516085579542783,
  "AverageFlitPerStateDelay[ROUTE_COMPUTATION]": 1.05989246241163,
  "AverageFlitPerStateDelay[VIRTUAL_CHANNEL_ALLOCATION]": 1.063566260261545,
  "AverageFlitPerStateDelay[SWITCH_ALLOCATION]": 1,
  "AverageFlitPerStateDelay[SWITCH_TRAVERSAL]": 1.0063093576819404,
  "AverageFlitPerStateDelay[LINK_TRAVERSAL]": 1.3218165290626813,
  "AverageFlitPerStateDelay[DESTINATION_ARRIVED]": 0,
  "MaxFlitPerStateDelay[INPUT_BUFFER]": 42,
  "MaxFlitPerStateDelay[ROUTE_COMPUTATION]": 28,
  "MaxFlitPerStateDelay[VIRTUAL_CHANNEL_ALLOCATION]": 4,
  "MaxFlitPerStateDelay[SWITCH_ALLOCATION]": 1,
  "MaxFlitPerStateDelay[SWITCH_TRAVERSAL]": 30,
  "MaxFlitPerStateDelay[LINK_TRAVERSAL]": 55,
  "MaxFlitPerStateDelay[DESTINATION_ARRIVED]": 0
}