{
  "SimulationTime": "21m50.673007683s",
  "SimulationTimeInSeconds": 1310.673007683,
  "TotalCycles": 1000000,
  "CyclesPerSecond": 762.9668072342423,
  "PacketsPerSecond": 4392.933223045789,
  "NumPacketsReceived": 5757982,
  "NumPacketsTransmitted": 5757699,
  "Throughput": 0.089964046875,
  "AveragePacketDelay": 49.32125593922155,
  "AveragePacketHops": 6.334108295692428,
  "MaxPacketDelay": 274,
  "MaxPacketHops": 15,
  "NumPayloadPacketsReceived": 5757982,
  "NumPayloadPacketsTransmitted": 5757699,
  "PayloadThroughput": 0.089964046875,
  "AveragePayloadPacketDelay": 49.32125593922155,
  "AveragePayloadPacketHops": 6.334108295692428,
  "MaxPayloadPacketDelay": 274,
  "MaxPayloadPacketHops": 15,
  "AverageFlitPerStateDelay[INPUT_BUFFER]": 3.3738561946612085,
  "AverageFlitPerStateDelay[ROUTE_COMPUTATION]": 1.3395402407517978,
  "AverageFlitPerStateDelay[VIRTUAL_CHANNEL_ALLOCATION]": 1.26382175078101,
  "AverageFlitPerStateDelay[SWITCH_ALLOCATION]": 1,
  "AverageFlitPerStateDelay[SWITCH_TRAVERSAL]": 1.0022957740476581,
  "AverageFlitPerStateDelay[LINK_TRAVERSAL]": 1.3573564680590748,
  "AverageFlitPerStateDelay[DESTINATION_ARRIVED]": 0,
  "MaxFlitPerStateDelay[INPUT_BUFFER]": 82,
  "MaxFlitPerStateDelay[ROUTE_COMPUTATION]": 65,
  "MaxFlitPerStateDelay[VIRTUAL_CHANNEL_ALLOCATION]": 5,
  "MaxFlitPerStateDelay[SWITCH_ALLOCATION]": 1,
  "MaxFlitPerStateDelay[SWITCH_TRAVERSAL]": 58,
  "MaxFlitPerStateDelay[LINK_TRAVERSAL]": 101,
  "MaxFlitPerStateDelay[DESTINATION_ARRIVED]": 0
}