{
  "SimulationTime": "1.680813579s",
  "SimulationTimeInSeconds": 1.680813579,
  "TotalCycles": 1000,
  "CyclesPerSecond": 594.9499769004424,
  "PacketsPerSecond": 2134.085567141887,
  "NumPacketsReceived": 4181,
  "NumPacketsTransmitted": 3587,
  "Throughput": 0.056046875,
  "AveragePacketDelay": 88.12991357680512,
  "AveragePacketHops": 6.866183440200725,
  "MaxPacketDelay": 458,
  "MaxPacketHops": 15,
  "NumPayloadPacketsReceived": 4181,
  "NumPayloadPacketsTransmitted": 3587,
  "PayloadThroughput": 0.056046875,
  "AveragePayloadPacketDelay": 88.12991357680512,
  "AveragePayloadPacketHops": 6.866183440200725,
  "MaxPayloadPacketDelay": 458,
  "MaxPayloadPacketHops": 15,
  "AverageFlitPerStateDelay[INPUT_BUFFER]": 5.395366523752032,
  "AverageFlitPerStateDelay[ROUTE_COMPUTATION]": 2.2945493058970383,
  "AverageFlitPerStateDelay[VIRTUAL_CHANNEL_ALLOCATION]": 1.287159474102982,
  "AverageFlitPerStateDelay[SWITCH_ALLOCATION]": 1,
  "AverageFlitPerStateDelay[SWITCH_TRAVERSAL]": 1.2407849275583638,
  "AverageFlitPerStateDelay[LINK_TRAVERSAL]": 5.405464040885251,
  "AverageFlitPerStateDelay[DESTINATION_ARRIVED]": 0,
  "MaxFlitPerStateDelay[INPUT_BUFFER]": 214,
  "MaxFlitPerStateDelay[ROUTE_COMPUTATION]": 127,
  "MaxFlitPerStateDelay[VIRTUAL_CHANNEL_ALLOCATION]": 5,
  "MaxFlitPerStateDelay[SWITCH_ALLOCATION]": 1,
  "MaxFlitPerStateDelay[SWITCH_TRAVERSAL]": 129,
  "MaxFlitPerStateDelay[LINK_TRAVERSAL]": 210,
  "MaxFlitPerStateDelay[DESTINATION_ARRIVED]": 0
}