{
  "SimulationTime": "12.597970741s",
  "SimulationTimeInSeconds": 12.597970741,
  "TotalCycles": 100000,
  "CyclesPerSecond": 7937.78633526674,
  "PacketsPerSecond": 2105.0215582493865,
  "NumPacketsReceived": 26538,
  "NumPacketsTransmitted": 26519,
  "Throughput": 0.00414359375,
  "AveragePacketDelay": 87.51189713035936,
  "AveragePacketHops": 8.081073946981409,
  "MaxPacketDelay": 382,
  "MaxPacketHops": 14,
  "NumPayloadPacketsReceived": 24056,
  "NumPayloadPacketsTransmitted": 24038,
  "PayloadThroughput": 0.0037559375,
  "AveragePayloadPacketDelay": 93.05611947749397,
  "AveragePayloadPacketHops": 8.249313586820866,
  "MaxPayloadPacketDelay": 382,
  "MaxPayloadPacketHops": 14,
  "AverageFlitPerStateDelay[INPUT_BUFFER]": 3.8970983717330587,
  "AverageFlitPerStateDelay[ROUTE_COMPUTATION]": 1.2958725331517353,
  "AverageFlitPerStateDelay[VIRTUAL_CHANNEL_ALLOCATION]": 1.0955823705286136,
  "AverageFlitPerStateDelay[SWITCH_ALLOCATION]": 1,
  "AverageFlitPerStateDelay[SWITCH_TRAVERSAL]": 1.1538004457160365,
  "AverageFlitPerStateDelay[LINK_TRAVERSAL]": 4.22020190367934,
  "AverageFlitPerStateDelay[DESTINATION_ARRIVED]": 0,
  "MaxFlitPerStateDelay[INPUT_BUFFER]": 52,
  "MaxFlitPerStateDelay[ROUTE_COMPUTATION]": 39,
  "MaxFlitPerStateDelay[VIRTUAL_CHANNEL_ALLOCATION]": 5,
  "MaxFlitPerStateDelay[SWITCH_ALLOCATION]": 1,
  "MaxFlitPerStateDelay[SWITCH_TRAVERSAL]": 40,
  "MaxFlitPerStateDelay[LINK_TRAVERSAL]": 80,
  "MaxFlitPerStateDelay[DESTINATION_ARRIVED]": 0
}