{
  "SimulationTime": "4m16.533168914s",
  "SimulationTimeInSeconds": 256.533168914,
  "TotalCycles": 1000000,
  "CyclesPerSecond": 3898.131396549502,
  "PacketsPerSecond": 3843.483492501274,
  "NumPacketsReceived": 986020,
  "NumPacketsTransmitted": 985981,
  "Throughput": 0.015405953125,
  "AveragePacketDelay": 37.80558956004223,
  "AveragePacketHops": 6.334574398492466,
  "MaxPacketDelay": 92,
  "MaxPacketHops": 15,
  "NumPayloadPacketsReceived": 960264,
  "NumPayloadPacketsTransmitted": 960225,
  "PayloadThroughput": 0.015003515625,
  "AveragePayloadPacketDelay": 37.94821213778021,
  "AveragePayloadPacketHops": 6.3350568877086095,
  "MaxPayloadPacketDelay": 92,
  "MaxPayloadPacketHops": 15,
  "AverageFlitPerStateDelay[INPUT_BUFFER]": 2.150483895106378,
  "AverageFlitPerStateDelay[ROUTE_COMPUTATION]": 1.0009867209739447,
  "AverageFlitPerStateDelay[VIRTUAL_CHANNEL_ALLOCATION]": 1.0158893795370523,
  "AverageFlitPerStateDelay[SWITCH_ALLOCATION]": 1,
  "AverageFlitPerStateDelay[SWITCH_TRAVERSAL]": 1,
  "AverageFlitPerStateDelay[LINK_TRAVERSAL]": 1.0000338361245713,
  "AverageFlitPerStateDelay[DESTINATION_ARRIVED]": 0,
  "MaxFlitPerStateDelay[INPUT_BUFFER]": 26,
  "MaxFlitPerStateDelay[ROUTE_COMPUTATION]": 15,
  "MaxFlitPerStateDelay[VIRTUAL_CHANNEL_ALLOCATION]": 4,
  "MaxFlitPerStateDelay[SWITCH_ALLOCATION]": 1,
  "MaxFlitPerStateDelay[SWITCH_TRAVERSAL]": 1,
  "MaxFlitPerStateDelay[LINK_TRAVERSAL]": 9,
  "MaxFlitPerStateDelay[DESTINATION_ARRIVED]": 0
}