{
  "SimulationTime": "1h44m56.439994181s",
  "SimulationTimeInSeconds": 6296.439994181,
  "TotalCycles": 10000000,
  "CyclesPerSecond": 1588.199047277784,
  "PacketsPerSecond": 2709.2636498982292,
  "NumPacketsReceived": 17058792,
  "NumPacketsTransmitted": 17058716,
  "Throughput": 0.02665424375,
  "AveragePacketDelay": 42.3050041398192,
  "AveragePacketHops": 6.990530236859562,
  "MaxPacketDelay": 136,
  "MaxPacketHops": 15,
  "NumPayloadPacketsReceived": 16801491,
  "NumPayloadPacketsTransmitted": 16801418,
  "PayloadThroughput": 0.026252215625,
  "AveragePayloadPacketDelay": 42.44190067766899,
  "AveragePayloadPacketHops": 7.000586855228529,
  "MaxPayloadPacketDelay": 136,
  "MaxPayloadPacketHops": 15,
  "AverageFlitPerStateDelay[INPUT_BUFFER]": 2.214166420528805,
  "AverageFlitPerStateDelay[ROUTE_COMPUTATION]": 1.0387983691247464,
  "AverageFlitPerStateDelay[VIRTUAL_CHANNEL_ALLOCATION]": 1.0730995317225636,
  "AverageFlitPerStateDelay[SWITCH_ALLOCATION]": 1,
  "AverageFlitPerStateDelay[SWITCH_TRAVERSAL]": 1.000004439643595,
  "AverageFlitPerStateDelay[LINK_TRAVERSAL]": 1.0033492852397328,
  "AverageFlitPerStateDelay[DESTINATION_ARRIVED]": 0,
  "MaxFlitPerStateDelay[INPUT_BUFFER]": 43,
  "MaxFlitPerStateDelay[ROUTE_COMPUTATION]": 32,
  "MaxFlitPerStateDelay[VIRTUAL_CHANNEL_ALLOCATION]": 6,
  "MaxFlitPerStateDelay[SWITCH_ALLOCATION]": 1,
  "MaxFlitPerStateDelay[SWITCH_TRAVERSAL]": 18,
  "MaxFlitPerStateDelay[LINK_TRAVERSAL]": 49,
  "MaxFlitPerStateDelay[DESTINATION_ARRIVED]": 0
}