{
  "SimulationTime": "7m51.855687201s",
  "SimulationTimeInSeconds": 471.855687201,
  "TotalCycles": 10000000,
  "CyclesPerSecond": 21192.92035944079,
  "PacketsPerSecond": 2119.1564012537788,
  "NumPacketsReceived": 999941,
  "NumPacketsTransmitted": 999936,
  "Throughput": 0.0015624,
  "AveragePacketDelay": 50.64072600646441,
  "AveragePacketHops": 8.520782330069125,
  "MaxPacketDelay": 99,
  "MaxPacketHops": 14,
  "NumPayloadPacketsReceived": 999941,
  "NumPayloadPacketsTransmitted": 999936,
  "PayloadThroughput": 0.0015624,
  "AveragePayloadPacketDelay": 50.64072600646441,
  "AveragePayloadPacketHops": 8.520782330069125,
  "MaxPayloadPacketDelay": 99,
  "MaxPayloadPacketHops": 14,
  "AverageFlitPerStateDelay[INPUT_BUFFER]": 2.047279970963353,
  "AverageFlitPerStateDelay[ROUTE_COMPUTATION]": 1.0005300300272104,
  "AverageFlitPerStateDelay[VIRTUAL_CHANNEL_ALLOCATION]": 1.0248604768557243,
  "AverageFlitPerStateDelay[SWITCH_ALLOCATION]": 1,
  "AverageFlitPerStateDelay[SWITCH_TRAVERSAL]": 1,
  "AverageFlitPerStateDelay[LINK_TRAVERSAL]": 1.000082243750464,
  "AverageFlitPerStateDelay[DESTINATION_ARRIVED]": 0,
  "MaxFlitPerStateDelay[INPUT_BUFFER]": 22,
  "MaxFlitPerStateDelay[ROUTE_COMPUTATION]": 14,
  "MaxFlitPerStateDelay[VIRTUAL_CHANNEL_ALLOCATION]": 4,
  "MaxFlitPerStateDelay[SWITCH_ALLOCATION]": 1,
  "MaxFlitPerStateDelay[SWITCH_TRAVERSAL]": 1,
  "MaxFlitPerStateDelay[LINK_TRAVERSAL]": 12,
  "MaxFlitPerStateDelay[DESTINATION_ARRIVED]": 0
}