{
  "SimulationTime": "28.270155004s",
  "SimulationTimeInSeconds": 28.270155004,
  "TotalCycles": 100000,
  "CyclesPerSecond": 3537.2993174551325,
  "PacketsPerSecond": 970.9532896482593,
  "NumPacketsReceived": 27546,
  "NumPacketsTransmitted": 27449,
  "Throughput": 0.00428890625,
  "AveragePacketDelay": 330.1385478523808,
  "AveragePacketHops": 8.511712630696929,
  "MaxPacketDelay": 1421,
  "MaxPacketHops": 14,
  "NumPayloadPacketsReceived": 25064,
  "NumPayloadPacketsTransmitted": 24968,
  "PayloadThroughput": 0.00390125,
  "AveragePayloadPacketDelay": 357.9995594360782,
  "AveragePayloadPacketHops": 8.716477090676065,
  "MaxPayloadPacketDelay": 1421,
  "MaxPayloadPacketHops": 14,
  "AverageFlitPerStateDelay[INPUT_BUFFER]": 12.619058976802375,
  "AverageFlitPerStateDelay[ROUTE_COMPUTATION]": 3.7332570560083336,
  "AverageFlitPerStateDelay[VIRTUAL_CHANNEL_ALLOCATION]": 1.1476839004397388,
  "AverageFlitPerStateDelay[SWITCH_ALLOCATION]": 1,
  "AverageFlitPerStateDelay[SWITCH_TRAVERSAL]": 3.095194697504132,
  "AverageFlitPerStateDelay[LINK_TRAVERSAL]": 24.499351965027735,
  "AverageFlitPerStateDelay[DESTINATION_ARRIVED]": 0,
  "MaxFlitPerStateDelay[INPUT_BUFFER]": 169,
  "MaxFlitPerStateDelay[ROUTE_COMPUTATION]": 108,
  "MaxFlitPerStateDelay[VIRTUAL_CHANNEL_ALLOCATION]": 5,
  "MaxFlitPerStateDelay[SWITCH_ALLOCATION]": 1,
  "MaxFlitPerStateDelay[SWITCH_TRAVERSAL]": 112,
  "MaxFlitPerStateDelay[LINK_TRAVERSAL]": 280,
  "MaxFlitPerStateDelay[DESTINATION_ARRIVED]": 0
}