{
  "SimulationTime": "7.704750873s",
  "SimulationTimeInSeconds": 7.704750873,
  "TotalCycles": 100000,
  "CyclesPerSecond": 12979.004986447146,
  "PacketsPerSecond": 2274.051463675404,
  "NumPacketsReceived": 17533,
  "NumPacketsTransmitted": 17521,
  "Throughput": 0.00273765625,
  "AveragePacketDelay": 50.003881057017296,
  "AveragePacketHops": 8.426231379487472,
  "MaxPacketDelay": 101,
  "MaxPacketHops": 14,
  "NumPayloadPacketsReceived": 15051,
  "NumPayloadPacketsTransmitted": 15040,
  "PayloadThroughput": 0.00235,
  "AveragePayloadPacketDelay": 52.83816489361702,
  "AveragePayloadPacketHops": 8.752061170212766,
  "MaxPayloadPacketDelay": 101,
  "MaxPayloadPacketHops": 13,
  "AverageFlitPerStateDelay[INPUT_BUFFER]": 2.051624030529231,
  "AverageFlitPerStateDelay[ROUTE_COMPUTATION]": 1.0045433924448326,
  "AverageFlitPerStateDelay[VIRTUAL_CHANNEL_ALLOCATION]": 1.0326914222258334,
  "AverageFlitPerStateDelay[SWITCH_ALLOCATION]": 1,
  "AverageFlitPerStateDelay[SWITCH_TRAVERSAL]": 1.0000055281808231,
  "AverageFlitPerStateDelay[LINK_TRAVERSAL]": 1.0057288563536142,
  "AverageFlitPerStateDelay[DESTINATION_ARRIVED]": 0,
  "MaxFlitPerStateDelay[INPUT_BUFFER]": 26,
  "MaxFlitPerStateDelay[ROUTE_COMPUTATION]": 14,
  "MaxFlitPerStateDelay[VIRTUAL_CHANNEL_ALLOCATION]": 4,
  "MaxFlitPerStateDelay[SWITCH_ALLOCATION]": 1,
  "MaxFlitPerStateDelay[SWITCH_TRAVERSAL]": 2,
  "MaxFlitPerStateDelay[LINK_TRAVERSAL]": 20,
  "MaxFlitPerStateDelay[DESTINATION_ARRIVED]": 0
}