{
  "SimulationTime": "2h28m58.711427105s",
  "SimulationTimeInSeconds": 8938.711427105,
  "TotalCycles": 10000000,
  "CyclesPerSecond": 1118.729481486206,
  "PacketsPerSecond": 4324.270261459684,
  "NumPacketsReceived": 38653579,
  "NumPacketsTransmitted": 38653404,
  "Throughput": 0.06039594375,
  "AveragePacketDelay": 41.36517034825704,
  "AveragePacketHops": 6.333135886298655,
  "MaxPacketDelay": 209,
  "MaxPacketHops": 15,
  "NumPayloadPacketsReceived": 38396907,
  "NumPayloadPacketsTransmitted": 38396734,
  "PayloadThroughput": 0.059994896875,
  "AveragePayloadPacketDelay": 41.40118391319428,
  "AveragePayloadPacketHops": 6.333195995263556,
  "MaxPayloadPacketDelay": 209,
  "MaxPayloadPacketHops": 15,
  "AverageFlitPerStateDelay[INPUT_BUFFER]": 2.555455536236065,
  "AverageFlitPerStateDelay[ROUTE_COMPUTATION]": 1.1112641007603126,
  "AverageFlitPerStateDelay[VIRTUAL_CHANNEL_ALLOCATION]": 1.1466510980717313,
  "AverageFlitPerStateDelay[SWITCH_ALLOCATION]": 1,
  "AverageFlitPerStateDelay[SWITCH_TRAVERSAL]": 1.0000900657531726,
  "AverageFlitPerStateDelay[LINK_TRAVERSAL]": 1.0311988046749563,
  "AverageFlitPerStateDelay[DESTINATION_ARRIVED]": 0,
  "MaxFlitPerStateDelay[INPUT_BUFFER]": 73,
  "MaxFlitPerStateDelay[ROUTE_COMPUTATION]": 61,
  "MaxFlitPerStateDelay[VIRTUAL_CHANNEL_ALLOCATION]": 6,
  "MaxFlitPerStateDelay[SWITCH_ALLOCATION]": 1,
  "MaxFlitPerStateDelay[SWITCH_TRAVERSAL]": 51,
  "MaxFlitPerStateDelay[LINK_TRAVERSAL]": 90,
  "MaxFlitPerStateDelay[DESTINATION_ARRIVED]": 0
}