{
  "SimulationTime": "5m29.370939506s",
  "SimulationTimeInSeconds": 329.370939506,
  "TotalCycles": 10000000,
  "CyclesPerSecond": 30360.905594762815,
  "PacketsPerSecond": 2297.7862015850774,
  "NumPacketsReceived": 756829,
  "NumPacketsTransmitted": 756824,
  "Throughput": 0.0011825375,
  "AveragePacketDelay": 43.99848181347315,
  "AveragePacketHops": 7.775712715241588,
  "MaxPacketDelay": 86,
  "MaxPacketHops": 15,
  "NumPayloadPacketsReceived": 500174,
  "NumPayloadPacketsTransmitted": 500171,
  "PayloadThroughput": 0.0007815171875,
  "AveragePayloadPacketDelay": 50.06060527299663,
  "AveragePayloadPacketHops": 8.51646336952762,
  "MaxPayloadPacketDelay": 86,
  "MaxPayloadPacketHops": 14,
  "AverageFlitPerStateDelay[INPUT_BUFFER]": 1.8425921317122482,
  "AverageFlitPerStateDelay[ROUTE_COMPUTATION]": 1.0000394231978331,
  "AverageFlitPerStateDelay[VIRTUAL_CHANNEL_ALLOCATION]": 1.0068451925789228,
  "AverageFlitPerStateDelay[SWITCH_ALLOCATION]": 1,
  "AverageFlitPerStateDelay[SWITCH_TRAVERSAL]": 1,
  "AverageFlitPerStateDelay[LINK_TRAVERSAL]": 1.0000031694538762,
  "AverageFlitPerStateDelay[DESTINATION_ARRIVED]": 0,
  "MaxFlitPerStateDelay[INPUT_BUFFER]": 15,
  "MaxFlitPerStateDelay[ROUTE_COMPUTATION]": 9,
  "MaxFlitPerStateDelay[VIRTUAL_CHANNEL_ALLOCATION]": 4,
  "MaxFlitPerStateDelay[SWITCH_ALLOCATION]": 1,
  "MaxFlitPerStateDelay[SWITCH_TRAVERSAL]": 1,
  "MaxFlitPerStateDelay[LINK_TRAVERSAL]": 5,
  "MaxFlitPerStateDelay[DESTINATION_ARRIVED]": 0
}