{
  "SimulationTime": "26.773041618s",
  "SimulationTimeInSeconds": 26.773041618,
  "TotalCycles": 100000,
  "CyclesPerSecond": 3735.100457647225,
  "PacketsPerSecond": 1025.3224266287398,
  "NumPacketsReceived": 27546,
  "NumPacketsTransmitted": 27451,
  "Throughput": 0.00428921875,
  "AveragePacketDelay": 324.1290299078358,
  "AveragePacketHops": 8.691814505846782,
  "MaxPacketDelay": 1961,
  "MaxPacketHops": 14,
  "NumPayloadPacketsReceived": 25064,
  "NumPayloadPacketsTransmitted": 24970,
  "PayloadThroughput": 0.0039015625,
  "AveragePayloadPacketDelay": 350.9867040448538,
  "AveragePayloadPacketHops": 8.914457348818582,
  "MaxPayloadPacketDelay": 1961,
  "MaxPayloadPacketHops": 14,
  "AverageFlitPerStateDelay[INPUT_BUFFER]": 12.206197626370724,
  "AverageFlitPerStateDelay[ROUTE_COMPUTATION]": 3.7789812964557745,
  "AverageFlitPerStateDelay[VIRTUAL_CHANNEL_ALLOCATION]": 1.141516375281143,
  "AverageFlitPerStateDelay[SWITCH_ALLOCATION]": 1,
  "AverageFlitPerStateDelay[SWITCH_TRAVERSAL]": 3.0020161179384974,
  "AverageFlitPerStateDelay[LINK_TRAVERSAL]": 23.17146394381957,
  "AverageFlitPerStateDelay[DESTINATION_ARRIVED]": 0,
  "MaxFlitPerStateDelay[INPUT_BUFFER]": 363,
  "MaxFlitPerStateDelay[ROUTE_COMPUTATION]": 254,
  "MaxFlitPerStateDelay[VIRTUAL_CHANNEL_ALLOCATION]": 5,
  "MaxFlitPerStateDelay[SWITCH_ALLOCATION]": 1,
  "MaxFlitPerStateDelay[SWITCH_TRAVERSAL]": 273,
  "MaxFlitPerStateDelay[LINK_TRAVERSAL]": 525,
  "MaxFlitPerStateDelay[DESTINATION_ARRIVED]": 0
}