{
  "SimulationTime": "1.062588834s",
  "SimulationTimeInSeconds": 1.062588834,
  "TotalCycles": 1000,
  "CyclesPerSecond": 941.0977868416035,
  "PacketsPerSecond": 2940.930583880011,
  "NumPacketsReceived": 3347,
  "NumPacketsTransmitted": 3125,
  "Throughput": 0.048828125,
  "AveragePacketDelay": 55.58144,
  "AveragePacketHops": 6.904,
  "MaxPacketDelay": 257,
  "MaxPacketHops": 15,
  "NumPayloadPacketsReceived": 3333,
  "NumPayloadPacketsTransmitted": 3111,
  "PayloadThroughput": 0.048609375,
  "AveragePayloadPacketDelay": 55.729026036644164,
  "AveragePayloadPacketHops": 6.917711346833816,
  "MaxPayloadPacketDelay": 257,
  "MaxPayloadPacketHops": 15,
  "AverageFlitPerStateDelay[INPUT_BUFFER]": 3.4079726219804476,
  "AverageFlitPerStateDelay[ROUTE_COMPUTATION]": 1.510896527285613,
  "AverageFlitPerStateDelay[VIRTUAL_CHANNEL_ALLOCATION]": 1.2372798651466086,
  "AverageFlitPerStateDelay[SWITCH_ALLOCATION]": 1,
  "AverageFlitPerStateDelay[SWITCH_TRAVERSAL]": 1.0251975897957586,
  "AverageFlitPerStateDelay[LINK_TRAVERSAL]": 1.8402497197820817,
  "AverageFlitPerStateDelay[DESTINATION_ARRIVED]": 0,
  "MaxFlitPerStateDelay[INPUT_BUFFER]": 47,
  "MaxFlitPerStateDelay[ROUTE_COMPUTATION]": 31,
  "MaxFlitPerStateDelay[VIRTUAL_CHANNEL_ALLOCATION]": 5,
  "MaxFlitPerStateDelay[SWITCH_ALLOCATION]": 1,
  "MaxFlitPerStateDelay[SWITCH_TRAVERSAL]": 33,
  "MaxFlitPerStateDelay[LINK_TRAVERSAL]": 82,
  "MaxFlitPerStateDelay[DESTINATION_ARRIVED]": 0
}